{
    "/js/app.js": "/js/app.js",
    "/css/app.css": "/css/app.css",
    "/css/profile.css": "/css/profile.css",
    "/css/nav.css": "/css/nav.css",
    "/js/races-map.js": "/js/races-map.js",
    "/js/main.js": "/js/main.js",
    "/js/ajax.js": "/js/ajax.js",
    "/0.2d3a65afd88b66592131.hot-update.js": "/0.2d3a65afd88b66592131.hot-update.js",
    "/0.8cabf3ee19b29abb4091.hot-update.js": "/0.8cabf3ee19b29abb4091.hot-update.js",
    "/0.4f75c3f9ce568a432b58.hot-update.js": "/0.4f75c3f9ce568a432b58.hot-update.js",
    "/0.345d8afecefa5b658196.hot-update.js": "/0.345d8afecefa5b658196.hot-update.js",
    "/0.7e4cb9b33b814656e846.hot-update.js": "/0.7e4cb9b33b814656e846.hot-update.js",
    "/0.96b360cd245b93ced63c.hot-update.js": "/0.96b360cd245b93ced63c.hot-update.js",
    "/0.c7b478f906feb51c0a91.hot-update.js": "/0.c7b478f906feb51c0a91.hot-update.js",
    "/0.a1f5a3a5bdef31474b44.hot-update.js": "/0.a1f5a3a5bdef31474b44.hot-update.js",
    "/0.61542efa30b5dae8724c.hot-update.js": "/0.61542efa30b5dae8724c.hot-update.js",
    "/0.6cb6388fc1f034182e4a.hot-update.js": "/0.6cb6388fc1f034182e4a.hot-update.js",
    "/0.a646b8147812188d0890.hot-update.js": "/0.a646b8147812188d0890.hot-update.js",
    "/0.42636939fb348077ed37.hot-update.js": "/0.42636939fb348077ed37.hot-update.js",
    "/0.5a3867b081b9e7998d54.hot-update.js": "/0.5a3867b081b9e7998d54.hot-update.js",
    "/0.9ac175f0e192ef346083.hot-update.js": "/0.9ac175f0e192ef346083.hot-update.js",
    "/0.60a1875336a77de09c08.hot-update.js": "/0.60a1875336a77de09c08.hot-update.js",
    "/0.cc922b0100816e1e3124.hot-update.js": "/0.cc922b0100816e1e3124.hot-update.js",
    "/0.be3d596dd80af3ec647e.hot-update.js": "/0.be3d596dd80af3ec647e.hot-update.js",
    "/0.60733a2a208ff29b9c9c.hot-update.js": "/0.60733a2a208ff29b9c9c.hot-update.js",
    "/0.f9bdf7cfeebb97d46147.hot-update.js": "/0.f9bdf7cfeebb97d46147.hot-update.js",
    "/0.32329246bbdb7da64487.hot-update.js": "/0.32329246bbdb7da64487.hot-update.js",
    "/0.1c06f062f5c6862524cc.hot-update.js": "/0.1c06f062f5c6862524cc.hot-update.js",
    "/0.4c97fb4ef401139b9384.hot-update.js": "/0.4c97fb4ef401139b9384.hot-update.js",
    "/0.84c8afb570af8535756e.hot-update.js": "/0.84c8afb570af8535756e.hot-update.js",
    "/0.1f875f9fa56f6457a733.hot-update.js": "/0.1f875f9fa56f6457a733.hot-update.js",
    "/0.3bb24b933a4b3af10cc0.hot-update.js": "/0.3bb24b933a4b3af10cc0.hot-update.js",
    "/0.55f67ed4ed95b597611a.hot-update.js": "/0.55f67ed4ed95b597611a.hot-update.js",
    "/0.f3c49f411d815066ac37.hot-update.js": "/0.f3c49f411d815066ac37.hot-update.js",
    "/0.730ebc409bfaf6b769fc.hot-update.js": "/0.730ebc409bfaf6b769fc.hot-update.js",
    "/0.25584dc97333cc57b54a.hot-update.js": "/0.25584dc97333cc57b54a.hot-update.js",
    "/0.9684e9d33378d264fb69.hot-update.js": "/0.9684e9d33378d264fb69.hot-update.js",
    "/0.93cb7efc16903e7e99c1.hot-update.js": "/0.93cb7efc16903e7e99c1.hot-update.js",
    "/0.0033689926caa22901d3.hot-update.js": "/0.0033689926caa22901d3.hot-update.js",
    "/0.6fedf92232825ef6d93b.hot-update.js": "/0.6fedf92232825ef6d93b.hot-update.js",
    "/0.85990b0ad1c91e5b3b13.hot-update.js": "/0.85990b0ad1c91e5b3b13.hot-update.js",
    "/0.8ee2572e74f2abef52a3.hot-update.js": "/0.8ee2572e74f2abef52a3.hot-update.js",
    "/0.8cd998e358d16471dae7.hot-update.js": "/0.8cd998e358d16471dae7.hot-update.js",
    "/0.25dd6961903b9102781d.hot-update.js": "/0.25dd6961903b9102781d.hot-update.js",
    "/0.8ef20c7b6640ea0eb80d.hot-update.js": "/0.8ef20c7b6640ea0eb80d.hot-update.js",
    "/0.18625391b8b943f6aad4.hot-update.js": "/0.18625391b8b943f6aad4.hot-update.js",
    "/0.516c0ee187bdfae97ca7.hot-update.js": "/0.516c0ee187bdfae97ca7.hot-update.js",
    "/0.03b1614b3ad9cd0bbd99.hot-update.js": "/0.03b1614b3ad9cd0bbd99.hot-update.js",
    "/0.0b15c3c15d02fa1b6828.hot-update.js": "/0.0b15c3c15d02fa1b6828.hot-update.js",
    "/0.c2f95b0f56047dcb4d80.hot-update.js": "/0.c2f95b0f56047dcb4d80.hot-update.js",
    "/0.486f8f48db5a4f691d8f.hot-update.js": "/0.486f8f48db5a4f691d8f.hot-update.js",
    "/0.ae7d3976a15e63f9ee0c.hot-update.js": "/0.ae7d3976a15e63f9ee0c.hot-update.js",
    "/0.b35e4b5af85a8929df31.hot-update.js": "/0.b35e4b5af85a8929df31.hot-update.js",
    "/0.c1926b394b33b4f378f6.hot-update.js": "/0.c1926b394b33b4f378f6.hot-update.js",
    "/0.4b867280e01d26b16e80.hot-update.js": "/0.4b867280e01d26b16e80.hot-update.js",
    "/0.d9db74b8c98cba879406.hot-update.js": "/0.d9db74b8c98cba879406.hot-update.js",
    "/0.4db85501dc36286eb769.hot-update.js": "/0.4db85501dc36286eb769.hot-update.js",
    "/0.704a486c473216c56a97.hot-update.js": "/0.704a486c473216c56a97.hot-update.js",
    "/0.7622eb08c110fa3b2170.hot-update.js": "/0.7622eb08c110fa3b2170.hot-update.js",
    "/0.6af82b6baf74431674bb.hot-update.js": "/0.6af82b6baf74431674bb.hot-update.js",
    "/0.0084d0b0dfa5add22552.hot-update.js": "/0.0084d0b0dfa5add22552.hot-update.js",
    "/0.8a76c2da69aa205ee55b.hot-update.js": "/0.8a76c2da69aa205ee55b.hot-update.js",
    "/0.0818e246b653d1b33293.hot-update.js": "/0.0818e246b653d1b33293.hot-update.js",
    "/0.da6652d548778e662679.hot-update.js": "/0.da6652d548778e662679.hot-update.js",
    "/0.61565c2d58aef4fca632.hot-update.js": "/0.61565c2d58aef4fca632.hot-update.js",
    "/0.ef158ea2565f89dd0262.hot-update.js": "/0.ef158ea2565f89dd0262.hot-update.js",
    "/0.ab978c7f239dd1692357.hot-update.js": "/0.ab978c7f239dd1692357.hot-update.js",
    "/0.26379f8cf982645a65bb.hot-update.js": "/0.26379f8cf982645a65bb.hot-update.js",
    "/0.3f9ab709a6c9456bc86c.hot-update.js": "/0.3f9ab709a6c9456bc86c.hot-update.js",
    "/0.d1cfce964b0936912f04.hot-update.js": "/0.d1cfce964b0936912f04.hot-update.js",
    "/0.3b3b553d0316f3e48483.hot-update.js": "/0.3b3b553d0316f3e48483.hot-update.js",
    "/0.306fac2668811762abb3.hot-update.js": "/0.306fac2668811762abb3.hot-update.js",
    "/0.9158ff30b7c130a0d36d.hot-update.js": "/0.9158ff30b7c130a0d36d.hot-update.js",
    "/0.19d1f71e7f68f8602566.hot-update.js": "/0.19d1f71e7f68f8602566.hot-update.js",
    "/0.43658d728ac269629479.hot-update.js": "/0.43658d728ac269629479.hot-update.js",
    "/0.daaf0691c96132b7cca5.hot-update.js": "/0.daaf0691c96132b7cca5.hot-update.js",
    "/0.fbee2439f4b9e23a6e03.hot-update.js": "/0.fbee2439f4b9e23a6e03.hot-update.js",
    "/0.0d111376582422a0b54e.hot-update.js": "/0.0d111376582422a0b54e.hot-update.js",
    "/0.dcb5efc8ad2619f31f49.hot-update.js": "/0.dcb5efc8ad2619f31f49.hot-update.js",
    "/0.bf027eb3e833d8cdfeba.hot-update.js": "/0.bf027eb3e833d8cdfeba.hot-update.js",
    "/0.81c3156ef03811d76cdf.hot-update.js": "/0.81c3156ef03811d76cdf.hot-update.js",
    "/0.e45b5ba978488c6f6236.hot-update.js": "/0.e45b5ba978488c6f6236.hot-update.js",
    "/0.2c493bc5940baa1f38ed.hot-update.js": "/0.2c493bc5940baa1f38ed.hot-update.js",
    "/0.c1ba2e4e57f2f9eb161e.hot-update.js": "/0.c1ba2e4e57f2f9eb161e.hot-update.js",
    "/0.da1ffc8a1150f9beffa0.hot-update.js": "/0.da1ffc8a1150f9beffa0.hot-update.js",
    "/0.9a4d9cc167d2b3ec5f14.hot-update.js": "/0.9a4d9cc167d2b3ec5f14.hot-update.js",
    "/0.300fe0890a63abe2531c.hot-update.js": "/0.300fe0890a63abe2531c.hot-update.js",
    "/0.1685a8dd96949ba85532.hot-update.js": "/0.1685a8dd96949ba85532.hot-update.js",
    "/0.ddeb5aa760ed4f07d9f5.hot-update.js": "/0.ddeb5aa760ed4f07d9f5.hot-update.js",
    "/0.10624c9d96a3fc0eafc9.hot-update.js": "/0.10624c9d96a3fc0eafc9.hot-update.js",
    "/0.3ee832d2569e471e5f29.hot-update.js": "/0.3ee832d2569e471e5f29.hot-update.js",
    "/0.d2807388bbc33107df5e.hot-update.js": "/0.d2807388bbc33107df5e.hot-update.js",
    "/0.b9d283298b939d03caad.hot-update.js": "/0.b9d283298b939d03caad.hot-update.js",
    "/0.aae0e460e85b62b34596.hot-update.js": "/0.aae0e460e85b62b34596.hot-update.js",
    "/0.fd48dc198419512a4895.hot-update.js": "/0.fd48dc198419512a4895.hot-update.js",
    "/0.ca8171560d601ab4135a.hot-update.js": "/0.ca8171560d601ab4135a.hot-update.js",
    "/0.f9e7e3d56cbcf846b7e5.hot-update.js": "/0.f9e7e3d56cbcf846b7e5.hot-update.js",
    "/0.80cdda1101e49beeee23.hot-update.js": "/0.80cdda1101e49beeee23.hot-update.js",
    "/0.3bb6d89240b5a290191c.hot-update.js": "/0.3bb6d89240b5a290191c.hot-update.js",
    "/0.4fe48b622f68b5920500.hot-update.js": "/0.4fe48b622f68b5920500.hot-update.js",
    "/0.ead99e8c72f3a1a2adea.hot-update.js": "/0.ead99e8c72f3a1a2adea.hot-update.js",
    "/0.d722b76fc5a1e3d264e8.hot-update.js": "/0.d722b76fc5a1e3d264e8.hot-update.js",
    "/0.27332946d1a1d42a112c.hot-update.js": "/0.27332946d1a1d42a112c.hot-update.js",
    "/0.1e03a582544d8b0c6227.hot-update.js": "/0.1e03a582544d8b0c6227.hot-update.js",
    "/0.7fdca6341ebb7b48d58b.hot-update.js": "/0.7fdca6341ebb7b48d58b.hot-update.js",
    "/0.15ed411b92e946c57c8f.hot-update.js": "/0.15ed411b92e946c57c8f.hot-update.js",
    "/0.37e7a074e52b18add3cd.hot-update.js": "/0.37e7a074e52b18add3cd.hot-update.js",
    "/0.91ffaf3e40c16ccc52d9.hot-update.js": "/0.91ffaf3e40c16ccc52d9.hot-update.js",
    "/0.9d86dcdc011630b384fe.hot-update.js": "/0.9d86dcdc011630b384fe.hot-update.js",
    "/0.eb3efe221d97b66036ac.hot-update.js": "/0.eb3efe221d97b66036ac.hot-update.js",
    "/0.c4ae865375ae943f96db.hot-update.js": "/0.c4ae865375ae943f96db.hot-update.js",
    "/0.b439048bd95fce83dd2c.hot-update.js": "/0.b439048bd95fce83dd2c.hot-update.js",
    "/0.8ffc27e7bf52b2c2e720.hot-update.js": "/0.8ffc27e7bf52b2c2e720.hot-update.js",
    "/0.1ba80059d289b99fd3ae.hot-update.js": "/0.1ba80059d289b99fd3ae.hot-update.js",
    "/0.9c8b609c965fb5dd7871.hot-update.js": "/0.9c8b609c965fb5dd7871.hot-update.js",
    "/0.f228c0e883ed33ddfd2e.hot-update.js": "/0.f228c0e883ed33ddfd2e.hot-update.js",
    "/0.26654c9b82ff4b259a4d.hot-update.js": "/0.26654c9b82ff4b259a4d.hot-update.js",
    "/0.cdd9a4aa38ce77487057.hot-update.js": "/0.cdd9a4aa38ce77487057.hot-update.js",
    "/0.bd0f53d3f06a0d50f6f6.hot-update.js": "/0.bd0f53d3f06a0d50f6f6.hot-update.js",
    "/0.a3fb646ac2180fd77e7d.hot-update.js": "/0.a3fb646ac2180fd77e7d.hot-update.js",
    "/0.199c085ba3dc34af3de2.hot-update.js": "/0.199c085ba3dc34af3de2.hot-update.js",
    "/0.1de26df07ae63102c2a7.hot-update.js": "/0.1de26df07ae63102c2a7.hot-update.js",
    "/0.20c15e8e4518498c2487.hot-update.js": "/0.20c15e8e4518498c2487.hot-update.js",
    "/0.8a460048e5d7ce680818.hot-update.js": "/0.8a460048e5d7ce680818.hot-update.js",
    "/0.3227c6ba47aedddd6d03.hot-update.js": "/0.3227c6ba47aedddd6d03.hot-update.js",
    "/0.9a962e67a7fe6a66fe5c.hot-update.js": "/0.9a962e67a7fe6a66fe5c.hot-update.js",
    "/0.deb84871aa0a8cc32672.hot-update.js": "/0.deb84871aa0a8cc32672.hot-update.js",
    "/0.6ba7c4a8ecf2a5a0eabf.hot-update.js": "/0.6ba7c4a8ecf2a5a0eabf.hot-update.js",
    "/0.71b931828a4b3574a1b3.hot-update.js": "/0.71b931828a4b3574a1b3.hot-update.js",
    "/0.802964b0fcf1a92a1aa2.hot-update.js": "/0.802964b0fcf1a92a1aa2.hot-update.js",
    "/0.0ce28cf982602739cb48.hot-update.js": "/0.0ce28cf982602739cb48.hot-update.js",
    "/0.f01f95e8ed4762585f13.hot-update.js": "/0.f01f95e8ed4762585f13.hot-update.js",
    "/0.4d0f4d93df76a0292bf8.hot-update.js": "/0.4d0f4d93df76a0292bf8.hot-update.js",
    "/0.43ce3bc20515ee4b4905.hot-update.js": "/0.43ce3bc20515ee4b4905.hot-update.js",
    "/0.78f106fa202189a1bce0.hot-update.js": "/0.78f106fa202189a1bce0.hot-update.js",
    "/0.f93743d973668f3e1951.hot-update.js": "/0.f93743d973668f3e1951.hot-update.js",
    "/0.d678cb263e972c6f2349.hot-update.js": "/0.d678cb263e972c6f2349.hot-update.js",
    "/0.ed13d7c2ae9522f087cc.hot-update.js": "/0.ed13d7c2ae9522f087cc.hot-update.js",
    "/0.65afc928c58e7a9d3f89.hot-update.js": "/0.65afc928c58e7a9d3f89.hot-update.js",
    "/0.2fa2243221b7532fbddf.hot-update.js": "/0.2fa2243221b7532fbddf.hot-update.js",
    "/0.091eb913a37b44480303.hot-update.js": "/0.091eb913a37b44480303.hot-update.js",
    "/0.6a94b1c14a183d3beb82.hot-update.js": "/0.6a94b1c14a183d3beb82.hot-update.js",
    "/0.274de1cf42332293a33a.hot-update.js": "/0.274de1cf42332293a33a.hot-update.js",
    "/0.6885c7749f4837d6b7fc.hot-update.js": "/0.6885c7749f4837d6b7fc.hot-update.js",
    "/0.67f28311833734947490.hot-update.js": "/0.67f28311833734947490.hot-update.js",
    "/0.cbe6c1f366bc4a0b2e2c.hot-update.js": "/0.cbe6c1f366bc4a0b2e2c.hot-update.js",
    "/0.90272e373aff0205e917.hot-update.js": "/0.90272e373aff0205e917.hot-update.js",
    "/0.75d3d47624df0fa528c6.hot-update.js": "/0.75d3d47624df0fa528c6.hot-update.js",
    "/0.98a8932c98227ec776c7.hot-update.js": "/0.98a8932c98227ec776c7.hot-update.js",
    "/0.46ee5438cad53fefacc9.hot-update.js": "/0.46ee5438cad53fefacc9.hot-update.js",
    "/0.8f44323e78de55ea0ad6.hot-update.js": "/0.8f44323e78de55ea0ad6.hot-update.js",
    "/0.d1cfda0ff1370024278d.hot-update.js": "/0.d1cfda0ff1370024278d.hot-update.js",
    "/0.91a40af7436bf2ddebf3.hot-update.js": "/0.91a40af7436bf2ddebf3.hot-update.js",
    "/0.1b5f5899bcb763e81dbe.hot-update.js": "/0.1b5f5899bcb763e81dbe.hot-update.js",
    "/0.faace888e77fc473c0df.hot-update.js": "/0.faace888e77fc473c0df.hot-update.js",
    "/0.cb6e5c3935728e957051.hot-update.js": "/0.cb6e5c3935728e957051.hot-update.js",
    "/0.a37eed876eb9b3a9b84a.hot-update.js": "/0.a37eed876eb9b3a9b84a.hot-update.js",
    "/0.be3c1eab7636367c0a4d.hot-update.js": "/0.be3c1eab7636367c0a4d.hot-update.js",
    "/0.44c4c5bc0d561b87000b.hot-update.js": "/0.44c4c5bc0d561b87000b.hot-update.js",
    "/0.ace79e1a82c7eb167341.hot-update.js": "/0.ace79e1a82c7eb167341.hot-update.js",
    "/0.7d1698af616cc7f26055.hot-update.js": "/0.7d1698af616cc7f26055.hot-update.js",
    "/0.c681336f9a6e842e5421.hot-update.js": "/0.c681336f9a6e842e5421.hot-update.js",
    "/0.1d47cfc826b2b497471a.hot-update.js": "/0.1d47cfc826b2b497471a.hot-update.js",
    "/0.b8004da50b2793f5e60f.hot-update.js": "/0.b8004da50b2793f5e60f.hot-update.js",
    "/0.9185c5eddabab131b9fe.hot-update.js": "/0.9185c5eddabab131b9fe.hot-update.js",
    "/0.3769edb3bb3d359dc068.hot-update.js": "/0.3769edb3bb3d359dc068.hot-update.js",
    "/0.c445fdee3cb01546b640.hot-update.js": "/0.c445fdee3cb01546b640.hot-update.js",
    "/0.975a09696e4225b81d0f.hot-update.js": "/0.975a09696e4225b81d0f.hot-update.js",
    "/0.0ad864b3eb0466d3a9ca.hot-update.js": "/0.0ad864b3eb0466d3a9ca.hot-update.js",
    "/0.174e6770dbaf0295dea4.hot-update.js": "/0.174e6770dbaf0295dea4.hot-update.js",
    "/0.2d97e04f255efe40f2e1.hot-update.js": "/0.2d97e04f255efe40f2e1.hot-update.js",
    "/0.6913fbe98bba8f3ad19d.hot-update.js": "/0.6913fbe98bba8f3ad19d.hot-update.js",
    "/0.533cfe12e68424b75665.hot-update.js": "/0.533cfe12e68424b75665.hot-update.js",
    "/0.399fc5811f865b8afec3.hot-update.js": "/0.399fc5811f865b8afec3.hot-update.js",
    "/0.14e010a0382a3fb6e41a.hot-update.js": "/0.14e010a0382a3fb6e41a.hot-update.js",
    "/0.0d935898ffc5f36a84d1.hot-update.js": "/0.0d935898ffc5f36a84d1.hot-update.js",
    "/0.89dc9c1f5adc56e8b7b3.hot-update.js": "/0.89dc9c1f5adc56e8b7b3.hot-update.js",
    "/0.34f838a03455ee85c98c.hot-update.js": "/0.34f838a03455ee85c98c.hot-update.js",
    "/0.5ad2b765c2debc59353f.hot-update.js": "/0.5ad2b765c2debc59353f.hot-update.js",
    "/0.8aa20f7e7fe9970f77a9.hot-update.js": "/0.8aa20f7e7fe9970f77a9.hot-update.js",
    "/0.d0a9b51290f7b85a4d2f.hot-update.js": "/0.d0a9b51290f7b85a4d2f.hot-update.js",
    "/0.2a675e64b77a9e51d8ff.hot-update.js": "/0.2a675e64b77a9e51d8ff.hot-update.js",
    "/0.f53fbf66ce25dc9be9df.hot-update.js": "/0.f53fbf66ce25dc9be9df.hot-update.js",
    "/0.9f4b63a0841a70cb095f.hot-update.js": "/0.9f4b63a0841a70cb095f.hot-update.js",
    "/0.76df2ab31c9d145fb37b.hot-update.js": "/0.76df2ab31c9d145fb37b.hot-update.js",
    "/0.8ef133152f3ff31eb2ff.hot-update.js": "/0.8ef133152f3ff31eb2ff.hot-update.js",
    "/0.b8c91fff14f0b94d53b3.hot-update.js": "/0.b8c91fff14f0b94d53b3.hot-update.js",
    "/0.dc8beb4c7291312f7d09.hot-update.js": "/0.dc8beb4c7291312f7d09.hot-update.js",
    "/0.2d3e5e6bb8d6bb65213c.hot-update.js": "/0.2d3e5e6bb8d6bb65213c.hot-update.js",
    "/0.c1c183f1bb3816fa8899.hot-update.js": "/0.c1c183f1bb3816fa8899.hot-update.js",
    "/0.4697a7d77188fc5f67d8.hot-update.js": "/0.4697a7d77188fc5f67d8.hot-update.js",
    "/0.cd4fd93099b487f7082d.hot-update.js": "/0.cd4fd93099b487f7082d.hot-update.js",
    "/0.9fde4839ad0c4b72e12a.hot-update.js": "/0.9fde4839ad0c4b72e12a.hot-update.js",
    "/0.60e52e0230d4c8d75a33.hot-update.js": "/0.60e52e0230d4c8d75a33.hot-update.js",
    "/0.1d19cac0b988af5a1fe6.hot-update.js": "/0.1d19cac0b988af5a1fe6.hot-update.js",
    "/0.03bc244a96cbacdf2b6c.hot-update.js": "/0.03bc244a96cbacdf2b6c.hot-update.js",
    "/0.f3913dcf8b9de1e12ae6.hot-update.js": "/0.f3913dcf8b9de1e12ae6.hot-update.js",
    "/0.215d4c16f233b0847089.hot-update.js": "/0.215d4c16f233b0847089.hot-update.js",
    "/0.0854b6c50d802050c830.hot-update.js": "/0.0854b6c50d802050c830.hot-update.js",
    "/0.bdbed38fe784792ced6b.hot-update.js": "/0.bdbed38fe784792ced6b.hot-update.js"
}